eclipsebin/__init__.py
eclipsebin/binning.py
eclipsebin-0.4.0.dist-info/licenses/LICENSE
tests/__init__.py
tests/test_eclipsing_binary_binner.py
eclipsebin-0.4.0.dist-info/METADATA
eclipsebin-0.4.0.dist-info/WHEEL
eclipsebin-0.4.0.dist-info/top_level.txt
eclipsebin-0.4.0.dist-info/RECORD
