Metadata-Version: 2.4
Name: eclipsebin
Version: 0.4.0
Summary: A specialized binning scheme for eclipsing binary star light curves
Home-page: https://github.com/jackieblaum/eclipsebin
Author: Jackie Blaum
Author-email: jackie.blaum@gmail.com
Classifier: Programming Language :: Python :: 3
Classifier: License :: OSI Approved :: MIT License
Classifier: Operating System :: OS Independent
Requires-Python: >=3.9
License-File: LICENSE
Requires-Dist: numpy
Requires-Dist: pandas
Requires-Dist: scipy
Requires-Dist: matplotlib
Dynamic: author
Dynamic: author-email
Dynamic: classifier
Dynamic: description
Dynamic: description-content-type
Dynamic: home-page
Dynamic: license-file
Dynamic: requires-dist
Dynamic: requires-python
Dynamic: summary
